README.md
setup.py
taxi_tipee/__init__.py
taxi_tipee/backend.py
taxi_tipee.egg-info/PKG-INFO
taxi_tipee.egg-info/SOURCES.txt
taxi_tipee.egg-info/dependency_links.txt
taxi_tipee.egg-info/entry_points.txt
taxi_tipee.egg-info/requires.txt
taxi_tipee.egg-info/top_level.txt